src/hdl/bram/input_bram.sv
/* PASSED TESTS */

/*
 * Asynchronous input BRAM controller
 * reads network_input values from BRAM
 * and pushes them to mac_in and tile_idx
 */

module input_bram #(
    parameter integer BRAM_ADDR_WIDTH,
    parameter integer BRAM_DATA_WIDTH,
    parameter integer NETWORK_WIDTH,
    parameter integer MAX_TILES,
    parameter integer TILE_IDX_WIDTH,
    parameter integer MAX_NEURONS,
    parameter integer CROSSBAR_NEURONS
) (
    input wire clk, 
    input wire enable,

    input wire mac_out_fifo_full,
    input wire tile_idx_fifo_full,
    
    input wire mac_out_fifo_push_done,
    input wire tile_idx_fifo_push_done,

    output reg [CROSSBAR_NEURONS*NETWORK_WIDTH-1:0] mac_out_fifo_din,
    output reg [2*TILE_IDX_WIDTH-1:0] tile_idx_fifo_din,

    output reg mac_out_fifo_push,
    output reg tile_idx_fifo_push,

    output reg [BRAM_ADDR_WIDTH-1:0] addr,
    input wire [BRAM_DATA_WIDTH-1:0] dout,
    output reg [BRAM_DATA_WIDTH-1:0] din,
    output reg bram_en,
    output reg bram_rst,
    output reg [BRAM_DATA_WIDTH/8-1:0] bram_we,
    input wire bram_active // if this port is active in switcher
);
    localparam integer SEND = 0;
    localparam integer WAIT = 1;
    localparam integer INCREMENT = 2;

    localparam integer TILE_IDX_BITS = ((2*TILE_IDX_WIDTH*MAX_TILES) / BRAM_DATA_WIDTH + 1) * BRAM_DATA_WIDTH;
    localparam integer WEIGHT_BITS = ((MAX_TILES*CROSSBAR_NEURONS*CROSSBAR_NEURONS*NETWORK_WIDTH) / BRAM_DATA_WIDTH + 1) * BRAM_DATA_WIDTH;
    localparam integer NETWORK_INPUT_BITS = ((MAX_NEURONS*NETWORK_WIDTH) / BRAM_DATA_WIDTH + 1) * BRAM_DATA_WIDTH;
    localparam integer SPK_OUT_BITS = ((MAX_NEURONS) / BRAM_DATA_WIDTH + 1) * BRAM_DATA_WIDTH;
    localparam integer FLAGS_BITS = 1024;

    localparam integer TILE_IDX_OFFSET = 0;
    localparam integer WEIGHT_OFFSET = TILE_IDX_OFFSET + TILE_IDX_BITS / 8;
    localparam integer NETWORK_INPUT_OFFSET = WEIGHT_OFFSET + WEIGHT_BITS / 8;
    localparam integer SPK_OUT_OFFSET = NETWORK_INPUT_OFFSET + NETWORK_INPUT_BITS / 8;
    localparam integer FLAGS_OFFSET = SPK_OUT_OFFSET + SPK_OUT_BITS / 8;
    localparam integer MEM_OFFSET = FLAGS_OFFSET + FLAGS_BITS / 8;

    reg bram_done;
    reg [4:0] bram_step = SEND;

    wire fifo_done;
    assign fifo_done = (tile_idx_fifo_push_done || ~tile_idx_fifo_push) 
                    && (mac_out_fifo_push_done || ~mac_out_fifo_push_done);

    wire fifo_full;
    assign fifo_full = tile_idx_fifo_full || mac_out_fifo_full;

    wire tiles_done;
    reg [TILE_IDX_WIDTH-1:0] tile_idx;
    assign tiles_done = (tile_idx == (MAX_NEURONS / CROSSBAR_NEURONS));

    wire [11:0] tile_idx_base;
    assign tile_idx_base = tile_idx % (BRAM_DATA_WIDTH / CROSSBAR_NEURONS / NETWORK_WIDTH);
    wire [CROSSBAR_NEURONS*NETWORK_WIDTH-1:0] mac_out_slices[BRAM_DATA_WIDTH / CROSSBAR_NEURONS / NETWORK_WIDTH];
    
    generate
        genvar i, j;
        for(i = 0; i < BRAM_DATA_WIDTH / CROSSBAR_NEURONS / NETWORK_WIDTH; i++) begin
            for(j = 0; j < CROSSBAR_NEURONS; j++) begin
                assign mac_out_slices[i][j*NETWORK_WIDTH+NETWORK_WIDTH-1 : j*NETWORK_WIDTH] 
                    = dout[i*CROSSBAR_NEURONS*NETWORK_WIDTH+j*NETWORK_WIDTH+NETWORK_WIDTH-1 : i*CROSSBAR_NEURONS*NETWORK_WIDTH+j*NETWORK_WIDTH];
            end
        end
    endgenerate

    always @(posedge clk) begin
        if(~enable) begin
            bram_step <= SEND;
            tile_idx <= 0; 
            bram_en <= 0;
            bram_we <= 0;
        end else begin
            if(fifo_done && ~fifo_full && ~tiles_done) begin
                if(bram_step == SEND) begin
                    addr <= NETWORK_INPUT_OFFSET + tile_idx*CROSSBAR_NEURONS*NETWORK_WIDTH/8;
                    bram_we <= 0;
                    bram_en <= 1;
                    bram_done <= 0;
                    bram_step <= WAIT;
                    tile_idx_fifo_din <= (tile_idx << TILE_IDX_WIDTH) + tile_idx;
                end else if(bram_step == WAIT) begin
                    if(bram_done) begin
                        bram_en <= 0;
                        bram_step <= INCREMENT;
                        mac_out_fifo_din <= mac_out_slices[tile_idx_base];
                    end
                    else bram_done <= bram_active;
                end else if(bram_step == INCREMENT) begin
                    tile_idx <= tile_idx+1;
                    bram_step <= SEND;
                end
            end
        end
    end
endmodule

src/hdl/bram/dual_port_bram.sv
/* PASSED TESTS */

/*
 * FOR SIMULATION USE ONLY
 * USE BLOCK MEMORY GENERATOR IN DEPLOYMENT
 * True dual-port RAM
 */

module dual_port_bram #(
    parameter BRAM_DATA_WIDTH,
    parameter BRAM_ADDR_WIDTH
)(
    input wire clka,
    // Port A signals
    input wire [BRAM_ADDR_WIDTH-1:0] addra,
    input wire [BRAM_DATA_WIDTH-1:0] dina,
    output reg [BRAM_DATA_WIDTH-1:0] douta,
    input wire [BRAM_DATA_WIDTH/8-1:0] wea, // Byte-enable for write
    input wire ena,
    
    // Port B signals
    input wire clkb,
    input wire [BRAM_ADDR_WIDTH-1:0] addrb,
    input wire [BRAM_DATA_WIDTH-1:0] dinb,
    output reg [BRAM_DATA_WIDTH-1:0] doutb,
    input wire [BRAM_DATA_WIDTH/8-1:0] web, // Byte-enable for write
    input wire enb
);

    localparam LOG_WORD_WIDTH = $clog2(BRAM_DATA_WIDTH / 8);
    // BRAM memory declaration
    reg [BRAM_DATA_WIDTH-1:0] mem [1023:0];

    initial begin
        for(integer asdf = 0; asdf < 1024; asdf++) begin
            mem[asdf] = 0;
        end
        $readmemb("/home/andrew/Desktop/snn-soc/src/hdl/bram/bram.mem", mem);
    end

    integer i;

    // Port A: Read and Masked Write
    always @(posedge clka) begin
        if (ena) begin
            douta <= mem[addra >> LOG_WORD_WIDTH]; // Read data
            for (i = 0; i < BRAM_DATA_WIDTH/8; i = i + 1) begin
                if (wea[i]) begin
                    mem[addra >> LOG_WORD_WIDTH][i*8 +: 8] <= dina[i*8 +: 8];
                end
            end
        end
    end

    // Port B: Read and Masked Write
    always @(posedge clkb) begin
        if (enb) begin
            doutb <= mem[addrb >> LOG_WORD_WIDTH]; // Read data
            for (i = 0; i < BRAM_DATA_WIDTH/8; i = i + 1) begin
                if (web[i]) begin
                    mem[addrb >> LOG_WORD_WIDTH][i*8 +: 8] <= dinb[i*8 +: 8];
                end
            end
        end
    end

endmodule


/*module dual_port_bram#(
    parameter integer BRAM_DATA_WIDTH,
    parameter integer BRAM_ADDR_WIDTH
) (
    input wire clka,
    input wire ena,
    input wire [BRAM_DATA_WIDTH/8-1:0] wea,
    input wire [BRAM_ADDR_WIDTH-1:0] addra,
    input wire [BRAM_DATA_WIDTH-1:0] dina,
    output reg [BRAM_DATA_WIDTH-1:0] douta,

    input wire clkb,
    input wire enb,
    input wire [BRAM_DATA_WIDTH/8-1:0] web,
    input wire [BRAM_ADDR_WIDTH-1:0] addrb,
    input wire [BRAM_DATA_WIDTH-1:0] dinb,
    output reg [BRAM_DATA_WIDTH-1:0] doutb
);
    localparam LOG_WORD_WIDTH = $clog2(BRAM_DATA_WIDTH / 8);
    localparam LOG_BYTE_WIDTH = 7;

    reg [BRAM_DATA_WIDTH-1:0] memory[1024];

    initial begin
        for(integer asdf = 0; asdf < 1024; asdf++) begin
            memory[asdf] = 0;
        end
        $readmemb("bram.mem", memory);
    end

    always @(posedge clka) begin
        if(ena) begin
            if(|wea) begin
                memory[addra >>> LOG_BYTE_WIDTH] <= dina;
            end
            douta <= memory[addra >>> LOG_BYTE_WIDTH];
        end
    end

    always @(posedge clkb) begin
        if(enb) begin
            if(|web) begin
                memory[addrb >>> LOG_BYTE_WIDTH] <= dinb;
            end
            doutb <= memory[addrb >>> LOG_BYTE_WIDTH];
        end
    end
endmodule*/

src/hdl/bram/input_bram_tb.sv
`timescale 1ns / 10ps;
`include "input_bram.sv"
`include "dual_port_bram.sv"

module input_bram_tb;
    localparam BRAM_DATA_WIDTH = 1024;
    localparam BRAM_ADDR_WIDTH = 16;
    localparam NETWORK_WIDTH = 8;
    localparam MAX_TILES = 64;
    localparam TILE_IDX_WIDTH = 16;
    localparam MAX_NEURONS = 1024;
    localparam CROSSBAR_NEURONS = 16;

    reg clk; 
    reg enable;

    reg mac_out_fifo_full = 0;
    reg tile_idx_fifo_full = 0;

    reg mac_out_fifo_push_done = 1;
    reg tile_idx_fifo_push_done = 1;

    wire [CROSSBAR_NEURONS*NETWORK_WIDTH-1:0] mac_out_fifo_din;
    wire [2*TILE_IDX_WIDTH-1:0] tile_idx_fifo_din;

    wire mac_out_fifo_push;
    wire tile_idx_fifo_push;

    wire [BRAM_ADDR_WIDTH-1:0] addr;
    reg [BRAM_DATA_WIDTH-1:0] dout;
    wire [BRAM_DATA_WIDTH-1:0] din;
    wire bram_en;
    wire bram_rst;
    reg [BRAM_DATA_WIDTH/8-1:0] bram_we;
    reg bram_active; // if this port is active in switcher


    dual_port_bram #(
        .BRAM_DATA_WIDTH(BRAM_DATA_WIDTH),
        .BRAM_ADDR_WIDTH(BRAM_ADDR_WIDTH) 
    ) ram (
        .clka(clk),
        .ena(bram_en),
        .wea(bram_we),
        .addra(addr),
        .dina(din),
        .douta(dout)
    );

    input_bram #(
        .BRAM_DATA_WIDTH(BRAM_DATA_WIDTH),
        .BRAM_ADDR_WIDTH(BRAM_ADDR_WIDTH),
        .NETWORK_WIDTH(NETWORK_WIDTH),
        .MAX_TILES(MAX_TILES),
        .TILE_IDX_WIDTH(TILE_IDX_WIDTH),
        .MAX_NEURONS(MAX_NEURONS),
        .CROSSBAR_NEURONS(CROSSBAR_NEURONS)
    ) lif (
        .clk(clk),
        .enable(enable),
        .mac_out_fifo_full(mac_out_fifo_full),
        .tile_idx_fifo_full(tile_idx_fifo_full),
        .mac_out_fifo_push_done(mac_out_fifo_push_done),
        .tile_idx_fifo_push_done(tile_idx_fifo_push_done),
        .mac_out_fifo_din(mac_out_fifo_din),
        .tile_idx_fifo_din(tile_idx_fifo_din),

        .addr(addr),
        .dout(dout),
        .din(din),
        .bram_en(bram_en),
        .bram_rst(bram_rst),
        .bram_we(bram_we),
        .bram_active(bram_active)
    );

    initial begin
        forever #5 clk = ~clk;
    end

    initial begin
        $dumpfile(".wave/dump.vcd");
        $dumpvars(100, input_bram_tb);
        
        #0 clk = 0;
        #0 enable = 0;
        #0 bram_active = 1;
        
        #100 enable = 1;
       
        #10000
        #0 $finish;
    end
endmodule

src/hdl/bram/.wave/dump.vcd
$date
	Fri Dec 13 12:59:49 2024
$end
$version
	Icarus Verilog
$end
$timescale
	10ps
$end
$scope module input_bram_tb $end
$var wire 32 ! tile_idx_fifo_din [31:0] $end
$var wire 128 " mac_out_fifo_din [127:0] $end
$var wire 1024 # dout [1023:0] $end
$var wire 1024 $ din [1023:0] $end
$var wire 128 % bram_we [127:0] $end
$var wire 1 & bram_rst $end
$var wire 1 ' bram_en $end
$var wire 16 ( addr [15:0] $end
$var parameter 32 ) BRAM_ADDR_WIDTH $end
$var parameter 32 * BRAM_DATA_WIDTH $end
$var parameter 32 + CROSSBAR_NEURONS $end
$var parameter 32 , MAX_NEURONS $end
$var parameter 32 - MAX_TILES $end
$var parameter 32 . NETWORK_WIDTH $end
$var parameter 32 / TILE_IDX_WIDTH $end
$var reg 1 0 bram_active $end
$var reg 1 1 clk $end
$var reg 1 2 enable $end
$var reg 1 3 mac_out_fifo_full $end
$var reg 1 4 mac_out_fifo_push_done $end
$var reg 1 5 tile_idx_fifo_full $end
$var reg 1 6 tile_idx_fifo_push_done $end
$scope module lif $end
$var wire 1 0 bram_active $end
$var wire 1 1 clk $end
$var wire 1 2 enable $end
$var wire 1 7 fifo_done $end
$var wire 1 8 fifo_full $end
$var wire 1 3 mac_out_fifo_full $end
$var wire 1 4 mac_out_fifo_push_done $end
$var wire 1 5 tile_idx_fifo_full $end
$var wire 1 6 tile_idx_fifo_push_done $end
$var wire 1 9 tiles_done $end
$var wire 12 : tile_idx_base [11:0] $end
$var wire 1024 ; dout [1023:0] $end
$var parameter 32 < BRAM_ADDR_WIDTH $end
$var parameter 32 = BRAM_DATA_WIDTH $end
$var parameter 32 > CROSSBAR_NEURONS $end
$var parameter 32 ? FLAGS_BITS $end
$var parameter 32 @ FLAGS_OFFSET $end
$var parameter 32 A INCREMENT $end
$var parameter 32 B MAX_NEURONS $end
$var parameter 32 C MAX_TILES $end
$var parameter 32 D MEM_OFFSET $end
$var parameter 32 E NETWORK_INPUT_BITS $end
$var parameter 32 F NETWORK_INPUT_OFFSET $end
$var parameter 32 G NETWORK_WIDTH $end
$var parameter 32 H SEND $end
$var parameter 32 I SPK_OUT_BITS $end
$var parameter 32 J SPK_OUT_OFFSET $end
$var parameter 32 K TILE_IDX_BITS $end
$var parameter 32 L TILE_IDX_OFFSET $end
$var parameter 32 M TILE_IDX_WIDTH $end
$var parameter 32 N WAIT $end
$var parameter 32 O WEIGHT_BITS $end
$var parameter 32 P WEIGHT_OFFSET $end
$var reg 16 Q addr [15:0] $end
$var reg 1 R bram_done $end
$var reg 1 ' bram_en $end
$var reg 1 & bram_rst $end
$var reg 5 S bram_step [4:0] $end
$var reg 128 T bram_we [127:0] $end
$var reg 1024 U din [1023:0] $end
$var reg 128 V mac_out_fifo_din [127:0] $end
$var reg 1 W mac_out_fifo_push $end
$var reg 16 X tile_idx [15:0] $end
$var reg 32 Y tile_idx_fifo_din [31:0] $end
$var reg 1 Z tile_idx_fifo_push $end
$scope begin genblk1[0] $end
$var parameter 2 [ i $end
$scope begin genblk1[0] $end
$var parameter 2 \ j $end
$upscope $end
$scope begin genblk1[1] $end
$var parameter 2 ] j $end
$upscope $end
$scope begin genblk1[2] $end
$var parameter 3 ^ j $end
$upscope $end
$scope begin genblk1[3] $end
$var parameter 3 _ j $end
$upscope $end
$scope begin genblk1[4] $end
$var parameter 4 ` j $end
$upscope $end
$scope begin genblk1[5] $end
$var parameter 4 a j $end
$upscope $end
$scope begin genblk1[6] $end
$var parameter 4 b j $end
$upscope $end
$scope begin genblk1[7] $end
$var parameter 4 c j $end
$upscope $end
$scope begin genblk1[8] $end
$var parameter 5 d j $end
$upscope $end
$scope begin genblk1[9] $end
$var parameter 5 e j $end
$upscope $end
$scope begin genblk1[10] $end
$var parameter 5 f j $end
$upscope $end
$scope begin genblk1[11] $end
$var parameter 5 g j $end
$upscope $end
$scope begin genblk1[12] $end
$var parameter 5 h j $end
$upscope $end
$scope begin genblk1[13] $end
$var parameter 5 i j $end
$upscope $end
$scope begin genblk1[14] $end
$var parameter 5 j j $end
$upscope $end
$scope begin genblk1[15] $end
$var parameter 5 k j $end
$upscope $end
$upscope $end
$scope begin genblk1[1] $end
$var parameter 2 l i $end
$scope begin genblk1[0] $end
$var parameter 2 m j $end
$upscope $end
$scope begin genblk1[1] $end
$var parameter 2 n j $end
$upscope $end
$scope begin genblk1[2] $end
$var parameter 3 o j $end
$upscope $end
$scope begin genblk1[3] $end
$var parameter 3 p j $end
$upscope $end
$scope begin genblk1[4] $end
$var parameter 4 q j $end
$upscope $end
$scope begin genblk1[5] $end
$var parameter 4 r j $end
$upscope $end
$scope begin genblk1[6] $end
$var parameter 4 s j $end
$upscope $end
$scope begin genblk1[7] $end
$var parameter 4 t j $end
$upscope $end
$scope begin genblk1[8] $end
$var parameter 5 u j $end
$upscope $end
$scope begin genblk1[9] $end
$var parameter 5 v j $end
$upscope $end
$scope begin genblk1[10] $end
$var parameter 5 w j $end
$upscope $end
$scope begin genblk1[11] $end
$var parameter 5 x j $end
$upscope $end
$scope begin genblk1[12] $end
$var parameter 5 y j $end
$upscope $end
$scope begin genblk1[13] $end
$var parameter 5 z j $end
$upscope $end
$scope begin genblk1[14] $end
$var parameter 5 { j $end
$upscope $end
$scope begin genblk1[15] $end
$var parameter 5 | j $end
$upscope $end
$upscope $end
$scope begin genblk1[2] $end
$var parameter 3 } i $end
$scope begin genblk1[0] $end
$var parameter 2 ~ j $end
$upscope $end
$scope begin genblk1[1] $end
$var parameter 2 !" j $end
$upscope $end
$scope begin genblk1[2] $end
$var parameter 3 "" j $end
$upscope $end
$scope begin genblk1[3] $end
$var parameter 3 #" j $end
$upscope $end
$scope begin genblk1[4] $end
$var parameter 4 $" j $end
$upscope $end
$scope begin genblk1[5] $end
$var parameter 4 %" j $end
$upscope $end
$scope begin genblk1[6] $end
$var parameter 4 &" j $end
$upscope $end
$scope begin genblk1[7] $end
$var parameter 4 '" j $end
$upscope $end
$scope begin genblk1[8] $end
$var parameter 5 (" j $end
$upscope $end
$scope begin genblk1[9] $end
$var parameter 5 )" j $end
$upscope $end
$scope begin genblk1[10] $end
$var parameter 5 *" j $end
$upscope $end
$scope begin genblk1[11] $end
$var parameter 5 +" j $end
$upscope $end
$scope begin genblk1[12] $end
$var parameter 5 ," j $end
$upscope $end
$scope begin genblk1[13] $end
$var parameter 5 -" j $end
$upscope $end
$scope begin genblk1[14] $end
$var parameter 5 ." j $end
$upscope $end
$scope begin genblk1[15] $end
$var parameter 5 /" j $end
$upscope $end
$upscope $end
$scope begin genblk1[3] $end
$var parameter 3 0" i $end
$scope begin genblk1[0] $end
$var parameter 2 1" j $end
$upscope $end
$scope begin genblk1[1] $end
$var parameter 2 2" j $end
$upscope $end
$scope begin genblk1[2] $end
$var parameter 3 3" j $end
$upscope $end
$scope begin genblk1[3] $end
$var parameter 3 4" j $end
$upscope $end
$scope begin genblk1[4] $end
$var parameter 4 5" j $end
$upscope $end
$scope begin genblk1[5] $end
$var parameter 4 6" j $end
$upscope $end
$scope begin genblk1[6] $end
$var parameter 4 7" j $end
$upscope $end
$scope begin genblk1[7] $end
$var parameter 4 8" j $end
$upscope $end
$scope begin genblk1[8] $end
$var parameter 5 9" j $end
$upscope $end
$scope begin genblk1[9] $end
$var parameter 5 :" j $end
$upscope $end
$scope begin genblk1[10] $end
$var parameter 5 ;" j $end
$upscope $end
$scope begin genblk1[11] $end
$var parameter 5 <" j $end
$upscope $end
$scope begin genblk1[12] $end
$var parameter 5 =" j $end
$upscope $end
$scope begin genblk1[13] $end
$var parameter 5 >" j $end
$upscope $end
$scope begin genblk1[14] $end
$var parameter 5 ?" j $end
$upscope $end
$scope begin genblk1[15] $end
$var parameter 5 @" j $end
$upscope $end
$upscope $end
$scope begin genblk1[4] $end
$var parameter 4 A" i $end
$scope begin genblk1[0] $end
$var parameter 2 B" j $end
$upscope $end
$scope begin genblk1[1] $end
$var parameter 2 C" j $end
$upscope $end
$scope begin genblk1[2] $end
$var parameter 3 D" j $end
$upscope $end
$scope begin genblk1[3] $end
$var parameter 3 E" j $end
$upscope $end
$scope begin genblk1[4] $end
$var parameter 4 F" j $end
$upscope $end
$scope begin genblk1[5] $end
$var parameter 4 G" j $end
$upscope $end
$scope begin genblk1[6] $end
$var parameter 4 H" j $end
$upscope $end
$scope begin genblk1[7] $end
$var parameter 4 I" j $end
$upscope $end
$scope begin genblk1[8] $end
$var parameter 5 J" j $end
$upscope $end
$scope begin genblk1[9] $end
$var parameter 5 K" j $end
$upscope $end
$scope begin genblk1[10] $end
$var parameter 5 L" j $end
$upscope $end
$scope begin genblk1[11] $end
$var parameter 5 M" j $end
$upscope $end
$scope begin genblk1[12] $end
$var parameter 5 N" j $end
$upscope $end
$scope begin genblk1[13] $end
$var parameter 5 O" j $end
$upscope $end
$scope begin genblk1[14] $end
$var parameter 5 P" j $end
$upscope $end
$scope begin genblk1[15] $end
$var parameter 5 Q" j $end
$upscope $end
$upscope $end
$scope begin genblk1[5] $end
$var parameter 4 R" i $end
$scope begin genblk1[0] $end
$var parameter 2 S" j $end
$upscope $end
$scope begin genblk1[1] $end
$var parameter 2 T" j $end
$upscope $end
$scope begin genblk1[2] $end
$var parameter 3 U" j $end
$upscope $end
$scope begin genblk1[3] $end
$var parameter 3 V" j $end
$upscope $end
$scope begin genblk1[4] $end
$var parameter 4 W" j $end
$upscope $end
$scope begin genblk1[5] $end
$var parameter 4 X" j $end
$upscope $end
$scope begin genblk1[6] $end
$var parameter 4 Y" j $end
$upscope $end
$scope begin genblk1[7] $end
$var parameter 4 Z" j $end
$upscope $end
$scope begin genblk1[8] $end
$var parameter 5 [" j $end
$upscope $end
$scope begin genblk1[9] $end
$var parameter 5 \" j $end
$upscope $end
$scope begin genblk1[10] $end
$var parameter 5 ]" j $end
$upscope $end
$scope begin genblk1[11] $end
$var parameter 5 ^" j $end
$upscope $end
$scope begin genblk1[12] $end
$var parameter 5 _" j $end
$upscope $end
$scope begin genblk1[13] $end
$var parameter 5 `" j $end
$upscope $end
$scope begin genblk1[14] $end
$var parameter 5 a" j $end
$upscope $end
$scope begin genblk1[15] $end
$var parameter 5 b" j $end
$upscope $end
$upscope $end
$scope begin genblk1[6] $end
$var parameter 4 c" i $end
$scope begin genblk1[0] $end
$var parameter 2 d" j $end
$upscope $end
$scope begin genblk1[1] $end
$var parameter 2 e" j $end
$upscope $end
$scope begin genblk1[2] $end
$var parameter 3 f" j $end
$upscope $end
$scope begin genblk1[3] $end
$var parameter 3 g" j $end
$upscope $end
$scope begin genblk1[4] $end
$var parameter 4 h" j $end
$upscope $end
$scope begin genblk1[5] $end
$var parameter 4 i" j $end
$upscope $end
$scope begin genblk1[6] $end
$var parameter 4 j" j $end
$upscope $end
$scope begin genblk1[7] $end
$var parameter 4 k" j $end
$upscope $end
$scope begin genblk1[8] $end
$var parameter 5 l" j $end
$upscope $end
$scope begin genblk1[9] $end
$var parameter 5 m" j $end
$upscope $end
$scope begin genblk1[10] $end
$var parameter 5 n" j $end
$upscope $end
$scope begin genblk1[11] $end
$var parameter 5 o" j $end
$upscope $end
$scope begin genblk1[12] $end
$var parameter 5 p" j $end
$upscope $end
$scope begin genblk1[13] $end
$var parameter 5 q" j $end
$upscope $end
$scope begin genblk1[14] $end
$var parameter 5 r" j $end
$upscope $end
$scope begin genblk1[15] $end
$var parameter 5 s" j $end
$upscope $end
$upscope $end
$scope begin genblk1[7] $end
$var parameter 4 t" i $end
$scope begin genblk1[0] $end
$var parameter 2 u" j $end
$upscope $end
$scope begin genblk1[1] $end
$var parameter 2 v" j $end
$upscope $end
$scope begin genblk1[2] $end
$var parameter 3 w" j $end
$upscope $end
$scope begin genblk1[3] $end
$var parameter 3 x" j $end
$upscope $end
$scope begin genblk1[4] $end
$var parameter 4 y" j $end
$upscope $end
$scope begin genblk1[5] $end
$var parameter 4 z" j $end
$upscope $end
$scope begin genblk1[6] $end
$var parameter 4 {" j $end
$upscope $end
$scope begin genblk1[7] $end
$var parameter 4 |" j $end
$upscope $end
$scope begin genblk1[8] $end
$var parameter 5 }" j $end
$upscope $end
$scope begin genblk1[9] $end
$var parameter 5 ~" j $end
$upscope $end
$scope begin genblk1[10] $end
$var parameter 5 !# j $end
$upscope $end
$scope begin genblk1[11] $end
$var parameter 5 "# j $end
$upscope $end
$scope begin genblk1[12] $end
$var parameter 5 ## j $end
$upscope $end
$scope begin genblk1[13] $end
$var parameter 5 $# j $end
$upscope $end
$scope begin genblk1[14] $end
$var parameter 5 %# j $end
$upscope $end
$scope begin genblk1[15] $end
$var parameter 5 &# j $end
$upscope $end
$upscope $end
$upscope $end
$scope module ram $end
$var wire 16 '# addra [15:0] $end
$var wire 16 (# addrb [15:0] $end
$var wire 1 1 clka $end
$var wire 1 )# clkb $end
$var wire 1024 *# dina [1023:0] $end
$var wire 1024 +# dinb [1023:0] $end
$var wire 1 ' ena $end
$var wire 1 ,# enb $end
$var wire 128 -# wea [127:0] $end
$var wire 128 .# web [127:0] $end
$var parameter 32 /# BRAM_ADDR_WIDTH $end
$var parameter 32 0# BRAM_DATA_WIDTH $end
$var parameter 32 1# LOG_WORD_WIDTH $end
$var reg 1024 2# douta [1023:0] $end
$var reg 1024 3# doutb [1023:0] $end
$var integer 32 4# i [31:0] $end
$scope begin $ivl_for_loop0 $end
$var integer 32 5# asdf [31:0] $end
$upscope $end
$upscope $end
$upscope $end
$enddefinitions $end
$comment Show the parameter values. $end
$dumpall
b111 1#
b10000000000 0#
b10000 /#
b1111 &#
b1110 %#
b1101 $#
b1100 ##
b1011 "#
b1010 !#
b1001 ~"
b1000 }"
b111 |"
b110 {"
b101 z"
b100 y"
b11 x"
b10 w"
b1 v"
b0 u"
b111 t"
b1111 s"
b1110 r"
b1101 q"
b1100 p"
b1011 o"
b1010 n"
b1001 m"
b1000 l"
b111 k"
b110 j"
b101 i"
b100 h"
b11 g"
b10 f"
b1 e"
b0 d"
b110 c"
b1111 b"
b1110 a"
b1101 `"
b1100 _"
b1011 ^"
b1010 ]"
b1001 \"
b1000 ["
b111 Z"
b110 Y"
b101 X"
b100 W"
b11 V"
b10 U"
b1 T"
b0 S"
b101 R"
b1111 Q"
b1110 P"
b1101 O"
b1100 N"
b1011 M"
b1010 L"
b1001 K"
b1000 J"
b111 I"
b110 H"
b101 G"
b100 F"
b11 E"
b10 D"
b1 C"
b0 B"
b100 A"
b1111 @"
b1110 ?"
b1101 >"
b1100 ="
b1011 <"
b1010 ;"
b1001 :"
b1000 9"
b111 8"
b110 7"
b101 6"
b100 5"
b11 4"
b10 3"
b1 2"
b0 1"
b11 0"
b1111 /"
b1110 ."
b1101 -"
b1100 ,"
b1011 +"
b1010 *"
b1001 )"
b1000 ("
b111 '"
b110 &"
b101 %"
b100 $"
b11 #"
b10 ""
b1 !"
b0 ~
b10 }
b1111 |
b1110 {
b1101 z
b1100 y
b1011 x
b1010 w
b1001 v
b1000 u
b111 t
b110 s
b101 r
b100 q
b11 p
b10 o
b1 n
b0 m
b1 l
b1111 k
b1110 j
b1101 i
b1100 h
b1011 g
b1010 f
b1001 e
b1000 d
b111 c
b110 b
b101 a
b100 `
b11 _
b10 ^
b1 ]
b0 \
b0 [
b110000000 P
b100000010000000000 O
b1 N
b10000 M
b0 L
b110000000000 K
b100011010000000 J
b100000000000 I
b0 H
b1000 G
b100001000000000 F
b10010000000000 E
b100100000000000 D
b1000000 C
b10000000000 B
b10 A
b100011110000000 @
b10000000000 ?
b10000 >
b10000000000 =
b10000 <
b10000 /
b1000 .
b1000000 -
b10000000000 ,
b10000 +
b10000000000 *
b10000 )
$end
#0
$dumpvars
b10000000000 5#
bx 4#
bx 3#
bx 2#
bz .#
bx -#
z,#
bz +#
bx *#
z)#
bz (#
bx '#
xZ
bx Y
bx X
xW
bx V
bx U
bx T
b0 S
xR
bx Q
bx ;
bx :
x9
08
17
16
05
14
03
02
01
10
bx (
x'
x&
bx %
bx $
bx #
bx "
bx !
$end
#500
b0 :
09
b0 %
b0 T
b0 -#
0'
b0 X
11
#1000
01
#1500
11
#2000
01
#2500
11
#3000
01
#3500
11
#4000
01
#4500
11
#5000
01
#5500
11
#6000
01
#6500
11
#7000
01
#7500
11
#8000
01
#8500
11
#9000
01
#9500
11
#10000
01
12
#10500
b0 !
b0 Y
b1 S
0R
1'
b100001000000000 (
b100001000000000 Q
b100001000000000 '#
11
#11000
01
#11500
1R
b100000000000000010000000100000 #
b100000000000000010000000100000 ;
b100000000000000010000000100000 2#
b10000000 4#
11
#12000
01
#12500
b100000000000000010000000100000 "
b100000000000000010000000100000 V
b10 S
0'
b10000000 4#
11
#13000
01
#13500
b1 :
b0 S
b1 X
11
#14000
01
#14500
b10000000000000001 !
b10000000000000001 Y
b1 S
0R
1'
b100001000010000 (
b100001000010000 Q
b100001000010000 '#
11
#15000
01
#15500
1R
b10000000 4#
11
#16000
01
#16500
b0 "
b0 V
b10 S
0'
b10000000 4#
11
#17000
01
#17500
b10 :
b0 S
b10 X
11
#18000
01
#18500
b100000000000000010 !
b100000000000000010 Y
b1 S
0R
1'
b100001000100000 (
b100001000100000 Q
b100001000100000 '#
11
#19000
01
#19500
1R
b10000000 4#
11
#20000
01
#20500
b10 S
0'
b10000000 4#
11
#21000
01
#21500
b11 :
b0 S
b11 X
11
#22000
01
#22500
b110000000000000011 !
b110000000000000011 Y
b1 S
0R
1'
b100001000110000 (
b100001000110000 Q
b100001000110000 '#
11
#23000
01
#23500
1R
b10000000 4#
11
#24000
01
#24500
b10 S
0'
b10000000 4#
11
#25000
01
#25500
b100 :
b0 S
b100 X
11
#26000
01
#26500
b1000000000000000100 !
b1000000000000000100 Y
b1 S
0R
1'
b100001001000000 (
b100001001000000 Q
b100001001000000 '#
11
#27000
01
#27500
1R
b10000000 4#
11
#28000
01
#28500
b10 S
0'
b10000000 4#
11
#29000
01
#29500
b101 :
b0 S
b101 X
11
#30000
01
#30500
b1010000000000000101 !
b1010000000000000101 Y
b1 S
0R
1'
b100001001010000 (
b100001001010000 Q
b100001001010000 '#
11
#31000
01
#31500
1R
b10000000 4#
11
#32000
01
#32500
b10 S
0'
b10000000 4#
11
#33000
01
#33500
b110 :
b0 S
b110 X
11
#34000
01
#34500
b1100000000000000110 !
b1100000000000000110 Y
b1 S
0R
1'
b100001001100000 (
b100001001100000 Q
b100001001100000 '#
11
#35000
01
#35500
1R
b10000000 4#
11
#36000
01
#36500
b10 S
0'
b10000000 4#
11
#37000
01
#37500
b111 :
b0 S
b111 X
11
#38000
01
#38500
b1110000000000000111 !
b1110000000000000111 Y
b1 S
0R
1'
b100001001110000 (
b100001001110000 Q
b100001001110000 '#
11
#39000
01
#39500
1R
b10000000 4#
11
#40000
01
#40500
b10 S
0'
b10000000 4#
11
#41000
01
#41500
b0 :
b0 S
b1000 X
11
#42000
01
