src/hdl/scheduler/lif_scheduler.sv
/* PASSED TESTS */

/*
 * LIF Scheduler
 * Schedules LIFs (tells lif_array to enable)
 * by reading the synaptic crossbar FIFO values
 * if the FIFO is not empty, it schedules a LIF operation on that tile
 */

module lif_scheduler (
    input wire clk,
    input wire en,

    input wire lif_done,

    input wire mac_out_fifo_empty,
    input wire tile_idx_fifo_empty,

    input wire mac_out_fifo_pop_done,
    input wire tile_idx_fifo_pop_done,

    output reg mac_out_fifo_pop,
    output reg tile_idx_fifo_pop,

    output reg lif_en
);
    wire ready;
    wire pop_done;
    assign ready = ~(mac_out_fifo_empty || tile_idx_fifo_empty);
    assign pop_done = (mac_out_fifo_pop_done && tile_idx_fifo_pop_done) || ~(mac_out_fifo_pop || tile_idx_fifo_pop);

    always @(posedge clk) begin
        if(~en) begin
            lif_en <= 0;
            mac_out_fifo_pop <= 0;
            tile_idx_fifo_pop <= 0;
        end else begin
            if(ready && pop_done) begin
                if(~lif_done) begin
                    lif_en <= 1;
                    mac_out_fifo_pop <= 0;
                    tile_idx_fifo_pop <= 0;
                end else begin
                    lif_en <= 0;
                    mac_out_fifo_pop <= 1;
                    tile_idx_fifo_pop <= 1;
                end
            end else begin
                lif_en <= 0;
            end
        end
    end
endmodule

src/hdl/scheduler/lif_scheduler_tb.sv
`timescale 1ns / 10ps

`include "lif_scheduler.sv"

module lif_scheduler_tb;
    reg clk;
    reg en;
    reg lif_done;
    reg mac_out_fifo_empty;
    reg mac_out_fifo_pop_done;
    wire mac_out_fifo_pop; 
    reg tile_idx_fifo_empty;
    reg tile_idx_fifo_pop_done;
    wire tile_idx_fifo_pop;
    wire lif_en;

    lif_scheduler lif_scheduler_0 (
        .clk(clk),
        .en(en),
        .lif_done(lif_done),
        .mac_out_fifo_empty(mac_out_fifo_empty),
        .mac_out_fifo_pop(mac_out_fifo_pop),
        .mac_out_fifo_pop_done(mac_out_fifo_pop_done),
        .tile_idx_fifo_empty(tile_idx_fifo_empty),
        .tile_idx_fifo_pop(tile_idx_fifo_pop),
        .tile_idx_fifo_pop_done(tile_idx_fifo_pop_done),
        .lif_en(lif_en)
    );

    initial begin
        forever #5 clk <= ~clk;
    end

    initial begin
        $dumpfile(".wave/lif_scheduler_tb.vcd");
        $dumpvars(100, lif_scheduler_tb);

        #0
        clk = 0;
        en = 0;
        lif_done = 0;
        mac_out_fifo_empty = 0;
        mac_out_fifo_pop_done = 0;
        tile_idx_fifo_empty = 0;
        tile_idx_fifo_pop_done = 0;

        #50
        en = 1;

        #50 lif_done = 1;

        #10
        mac_out_fifo_pop_done = 1;
        tile_idx_fifo_pop_done = 1;

        #10 lif_done = 0;

        #50
        mac_out_fifo_empty = 1;
        tile_idx_fifo_empty = 1;

        #100 $finish;
    end
endmodule

src/hdl/scheduler/.wave/lif_scheduler_tb.vcd
$date
	Fri Dec 13 11:16:35 2024
$end
$version
	Icarus Verilog
$end
$timescale
	10ps
$end
$scope module lif_scheduler_tb $end
$var wire 1 ! tile_idx_fifo_pop $end
$var wire 1 " mac_out_fifo_pop $end
$var wire 1 # lif_en $end
$var reg 1 $ clk $end
$var reg 1 % en $end
$var reg 1 & lif_done $end
$var reg 1 ' mac_out_fifo_empty $end
$var reg 1 ( mac_out_fifo_pop_done $end
$var reg 1 ) tile_idx_fifo_empty $end
$var reg 1 * tile_idx_fifo_pop_done $end
$scope module lif_scheduler_0 $end
$var wire 1 $ clk $end
$var wire 1 % en $end
$var wire 1 & lif_done $end
$var wire 1 ' mac_out_fifo_empty $end
$var wire 1 ( mac_out_fifo_pop_done $end
$var wire 1 + pop_done $end
$var wire 1 , ready $end
$var wire 1 ) tile_idx_fifo_empty $end
$var wire 1 * tile_idx_fifo_pop_done $end
$var reg 1 # lif_en $end
$var reg 1 " mac_out_fifo_pop $end
$var reg 1 ! tile_idx_fifo_pop $end
$upscope $end
$upscope $end
$enddefinitions $end
$comment Show the parameter values. $end
$dumpall
$end
#0
$dumpvars
1,
x+
0*
0)
0(
0'
0&
0%
0$
x#
x"
x!
$end
#500
1+
0!
0"
0#
1$
#1000
0$
#1500
1$
#2000
0$
#2500
1$
#3000
0$
#3500
1$
#4000
0$
#4500
1$
#5000
0$
1%
#5500
1#
1$
#6000
0$
#6500
1$
#7000
0$
#7500
1$
#8000
0$
#8500
1$
#9000
0$
#9500
1$
#10000
0$
1&
#10500
0+
1!
1"
0#
1$
#11000
0$
1+
1*
1(
#11500
1$
#12000
0$
0&
#12500
0!
0"
1#
1$
#13000
0$
#13500
1$
#14000
0$
#14500
1$
#15000
0$
#15500
1$
#16000
0$
#16500
1$
#17000
0$
0,
1)
1'
#17500
0#
1$
