src/hdl/fifo/mem_in_fifo.sv
/**
 * fifo for input mem potential 
 */

/* PASSED TESTS */

module mem_in_fifo #(
	parameter integer CROSSBAR_NEURONS,
	parameter integer BRAM_DATA_WIDTH,
	parameter integer NETWORK_WIDTH,
	parameter integer LENGTH
)(
	input wire clk,
	input wire [CROSSBAR_NEURONS*NETWORK_WIDTH-1:0] din,
	input wire push,
	input wire pop,

	output wire signed [NETWORK_WIDTH-1:0] mem_in [CROSSBAR_NEURONS],
	output wire full,
	output wire empty,

	output reg push_done,
	output reg pop_done
);
	localparam WIDTH = CROSSBAR_NEURONS*NETWORK_WIDTH;

	reg [7:0] cnt = 0;
	reg [LENGTH*WIDTH-1:0] buffer = 0;
	generate
		genvar i, j;
		for(i = 0; i < CROSSBAR_NEURONS; i++) begin
			assign mem_in[i] = buffer[NETWORK_WIDTH*(i+1)-1 : NETWORK_WIDTH*i];
		end
	endgenerate

	assign full = (cnt >= LENGTH);
	assign empty = (cnt == 0);

	always @(posedge clk) begin
		if(pop && ~pop_done) begin
			buffer <= (buffer >> WIDTH);
			pop_done <= 1;
			if(~empty) begin
				cnt <= cnt-1;
			end
		end	else if(push && ~push_done) begin
			if(~full) begin
				buffer <= (buffer | (din << (cnt*WIDTH)));
				cnt <= cnt+1;	
			end
			push_done <= 1;
		end

		if(~pop) begin
			pop_done <= 0;
		end
		if(~push) begin
			push_done <= 0;
		end
	end
endmodule

src/hdl/fifo/fifo_tb.sv
`timescale 1ns / 1ps;
`include "mem_in_fifo.sv"

module fifo_tb;
	localparam integer CROSSBAR_NEURONS = 16;
	localparam integer BRAM_DATA_WIDTH = 1024;
	localparam integer NETWORK_WIDTH = 8;
	localparam integer LENGTH = 2;

	reg clk = 0;
	reg [CROSSBAR_NEURONS*NETWORK_WIDTH-1:0] din = 0;
	reg push = 0;
	reg pop = 0;

	wire signed [NETWORK_WIDTH-1:0] mem_in [CROSSBAR_NEURONS];
	wire full;
	wire empty;

	wire push_done;
	wire pop_done;


	mem_in_fifo #(
		.CROSSBAR_NEURONS(CROSSBAR_NEURONS),
		.BRAM_DATA_WIDTH(BRAM_DATA_WIDTH),
		.NETWORK_WIDTH(NETWORK_WIDTH),
		.LENGTH(LENGTH)
	) fifo (
		.clk(clk),
		.din(din),
		.push(push),
		.pop(pop),
		.mem_in(mem_in),
		.full(full),
		.empty(empty),
		.push_done(push_done),
		.pop_done(pop_done)
	);
	initial begin
		forever begin
			#5 clk = ~clk;
		end	
	end

	initial begin
		$dumpfile("fifo_tb.vcd");
		$dumpvars(100, fifo_tb);
		#100 din <= 5;
		#200 push <= 1;
		#300 push <= 0;
		#400 push <= 1;
		#500 push <= 0;
		#600 pop <= 1;
		#700 pop <= 0;
		#800 pop <= 1;
		#900 pop <= 0;
		#1000 $finish;
	end
endmodule

src/hdl/fifo/fifo_tb.vcd
$date
	Wed Dec 11 15:23:17 2024
$end
$version
	Icarus Verilog
$end
$timescale
	1ps
$end
$scope module fifo_tb $end
$var wire 1 ! push_done $end
$var wire 1 " pop_done $end
$var wire 1 # full $end
$var wire 1 $ empty $end
$var parameter 32 % BRAM_DATA_WIDTH $end
$var parameter 32 & CROSSBAR_NEURONS $end
$var parameter 32 ' LENGTH $end
$var parameter 32 ( NETWORK_WIDTH $end
$var reg 1 ) clk $end
$var reg 128 * din [127:0] $end
$var reg 1 + pop $end
$var reg 1 , push $end
$scope module fifo $end
$var wire 1 ) clk $end
$var wire 128 - din [127:0] $end
$var wire 1 + pop $end
$var wire 1 , push $end
$var wire 1 # full $end
$var wire 1 $ empty $end
$var parameter 32 . BRAM_DATA_WIDTH $end
$var parameter 32 / CROSSBAR_NEURONS $end
$var parameter 32 0 LENGTH $end
$var parameter 32 1 NETWORK_WIDTH $end
$var parameter 64 2 WIDTH $end
$var reg 256 3 buffer [255:0] $end
$var reg 8 4 cnt [7:0] $end
$var reg 1 " pop_done $end
$var reg 1 ! push_done $end
$scope begin genblk1[0] $end
$var parameter 2 5 i $end
$upscope $end
$scope begin genblk1[1] $end
$var parameter 2 6 i $end
$upscope $end
$scope begin genblk1[2] $end
$var parameter 3 7 i $end
$upscope $end
$scope begin genblk1[3] $end
$var parameter 3 8 i $end
$upscope $end
$scope begin genblk1[4] $end
$var parameter 4 9 i $end
$upscope $end
$scope begin genblk1[5] $end
$var parameter 4 : i $end
$upscope $end
$scope begin genblk1[6] $end
$var parameter 4 ; i $end
$upscope $end
$scope begin genblk1[7] $end
$var parameter 4 < i $end
$upscope $end
$scope begin genblk1[8] $end
$var parameter 5 = i $end
$upscope $end
$scope begin genblk1[9] $end
$var parameter 5 > i $end
$upscope $end
$scope begin genblk1[10] $end
$var parameter 5 ? i $end
$upscope $end
$scope begin genblk1[11] $end
$var parameter 5 @ i $end
$upscope $end
$scope begin genblk1[12] $end
$var parameter 5 A i $end
$upscope $end
$scope begin genblk1[13] $end
$var parameter 5 B i $end
$upscope $end
$scope begin genblk1[14] $end
$var parameter 5 C i $end
$upscope $end
$scope begin genblk1[15] $end
$var parameter 5 D i $end
$upscope $end
$upscope $end
$upscope $end
$enddefinitions $end
$comment Show the parameter values. $end
$dumpall
b1111 D
b1110 C
b1101 B
b1100 A
b1011 @
b1010 ?
b1001 >
b1000 =
b111 <
b110 ;
b101 :
b100 9
b11 8
b10 7
b1 6
b0 5
b10000000 2
b1000 1
b10 0
b10000 /
b10000000000 .
b1000 (
b10 '
b10000 &
b10000000000 %
$end
#0
$dumpvars
b0 4
b0 3
b0 -
0,
0+
b0 *
0)
1$
0#
x"
x!
$end
#5000
0!
0"
1)
#10000
0)
#15000
1)
#20000
0)
#25000
1)
#30000
0)
#35000
1)
#40000
0)
#45000
1)
#50000
0)
#55000
1)
#60000
0)
#65000
1)
#70000
0)
#75000
1)
#80000
0)
#85000
1)
#90000
0)
#95000
1)
#100000
b101 *
b101 -
0)
#105000
1)
#110000
0)
#115000
1)
#120000
0)
#125000
1)
#130000
0)
#135000
1)
#140000
0)
#145000
1)
#150000
0)
#155000
1)
#160000
0)
#165000
1)
#170000
0)
#175000
1)
#180000
0)
#185000
1)
#190000
0)
#195000
1)
#200000
0)
#205000
1)
#210000
0)
#215000
1)
#220000
0)
#225000
1)
#230000
0)
#235000
1)
#240000
0)
#245000
1)
#250000
0)
#255000
1)
#260000
0)
#265000
1)
#270000
0)
#275000
1)
#280000
0)
#285000
1)
#290000
0)
#295000
1)
#300000
1,
0)
#305000
1!
0$
b1 4
b101 3
1)
#310000
0)
#315000
1)
#320000
0)
#325000
1)
#330000
0)
#335000
1)
#340000
0)
#345000
1)
#350000
0)
#355000
1)
#360000
0)
#365000
1)
#370000
0)
#375000
1)
#380000
0)
#385000
1)
#390000
0)
#395000
1)
#400000
0)
#405000
1)
#410000
0)
#415000
1)
#420000
0)
#425000
1)
#430000
0)
#435000
1)
#440000
0)
#445000
1)
#450000
0)
#455000
1)
#460000
0)
#465000
1)
#470000
0)
#475000
1)
#480000
0)
#485000
1)
#490000
0)
#495000
1)
#500000
0)
#505000
1)
#510000
0)
#515000
1)
#520000
0)
#525000
1)
#530000
0)
#535000
1)
#540000
0)
#545000
1)
#550000
0)
#555000
1)
#560000
0)
#565000
1)
#570000
0)
#575000
1)
#580000
0)
#585000
1)
#590000
0)
#595000
1)
#600000
0,
0)
#605000
0!
1)
#610000
0)
#615000
1)
#620000
0)
#625000
1)
#630000
0)
#635000
1)
#640000
0)
#645000
1)
#650000
0)
#655000
1)
#660000
0)
#665000
1)
#670000
0)
#675000
1)
#680000
0)
#685000
1)
#690000
0)
#695000
1)
#700000
0)
#705000
1)
#710000
0)
#715000
1)
#720000
0)
#725000
1)
#730000
0)
#735000
1)
#740000
0)
#745000
1)
#750000
0)
#755000
1)
#760000
0)
#765000
1)
#770000
0)
#775000
1)
#780000
0)
#785000
1)
#790000
0)
#795000
1)
#800000
0)
#805000
1)
#810000
0)
#815000
1)
#820000
0)
#825000
1)
#830000
0)
#835000
1)
#840000
0)
#845000
1)
#850000
0)
#855000
1)
#860000
0)
#865000
1)
#870000
0)
#875000
1)
#880000
0)
#885000
1)
#890000
0)
#895000
1)
#900000
0)
#905000
1)
#910000
0)
#915000
1)
#920000
0)
#925000
1)
#930000
0)
#935000
1)
#940000
0)
#945000
1)
#950000
0)
#955000
1)
#960000
0)
#965000
1)
#970000
0)
#975000
1)
#980000
0)
#985000
1)
#990000
0)
#995000
1)
#1000000
1,
0)
#1005000
1!
1#
b10 4
b10100000000000000000000000000000000000000000000000000000000000000000000000000000000000000000000000000000000000000000000000000000101 3
1)
